{"uri":"http:\/\/api.twitter.com\/1\/users\/show.json?user_id=35739323","name":"Aljoscha Gratt","screen_name":"leningratt","location":{"http:\/\/ws.geonames.org\/searchJSON?q=Graz,Austria":{"http:\/\/www.w3.org\/1999\/02\/22-rdf-syntax-ns#type":[{"value":"http:\/\/www.w3.org\/2003\/01\/geo\/wgs84_pos#Point","type":"uri"}],"http:\/\/www.w3.org\/2000\/01\/rdf-schema#seeAlso":[{"value":"http:\/\/sws.geonames.org\/2778067\/about.rdf","type":"uri"}],"http:\/\/www.w3.org\/2000\/01\/rdf-schema#link":[{"value":"http:\/\/www.geonames.org\/2778067","type":"uri"}],"http:\/\/www.w3.org\/2000\/01\/rdf-schema#label":[{"value":"Graz","type":"literal"}],"http:\/\/www.geonames.org\/ontology#countryCode":[{"value":"AT","type":"literal"}],"http:\/\/www.w3.org\/2003\/01\/geo\/wgs84_pos#long":[{"value":"15.45","type":"literal"}],"http:\/\/www.w3.org\/2003\/01\/geo\/wgs84_pos#lat":[{"value":"47.0666667","type":"literal"}]}},"image":["http:\/\/a3.twimg.com\/profile_images\/533287983\/twitterProfilePhoto_normal.jpg"],"description":["terrorist"],"friends":["http:\/\/api.twitter.com\/1\/users\/show.json?user_id=84269801","http:\/\/api.twitter.com\/1\/users\/show.json?user_id=18267528","http:\/\/api.twitter.com\/1\/users\/show.json?user_id=49768990","http:\/\/api.twitter.com\/1\/users\/show.json?user_id=6413902","http:\/\/api.twitter.com\/1\/users\/show.json?user_id=211235703","http:\/\/api.twitter.com\/1\/users\/show.json?user_id=62578858","http:\/\/api.twitter.com\/1\/users\/show.json?user_id=250185898","http:\/\/api.twitter.com\/1\/users\/show.json?user_id=95166028","http:\/\/api.twitter.com\/1\/users\/show.json?user_id=130375462","http:\/\/api.twitter.com\/1\/users\/show.json?user_id=119360445","http:\/\/api.twitter.com\/1\/users\/show.json?user_id=84599737","http:\/\/api.twitter.com\/1\/users\/show.json?user_id=18460608","http:\/\/api.twitter.com\/1\/users\/show.json?user_id=141142778","http:\/\/api.twitter.com\/1\/users\/show.json?user_id=30878503","http:\/\/api.twitter.com\/1\/users\/show.json?user_id=79836429","http:\/\/api.twitter.com\/1\/users\/show.json?user_id=26265158","http:\/\/api.twitter.com\/1\/users\/show.json?user_id=31412390","http:\/\/api.twitter.com\/1\/users\/show.json?user_id=85200786","http:\/\/api.twitter.com\/1\/users\/show.json?user_id=16079787","http:\/\/api.twitter.com\/1\/users\/show.json?user_id=14283602","http:\/\/api.twitter.com\/1\/users\/show.json?user_id=85081146","http:\/\/api.twitter.com\/1\/users\/show.json?user_id=1409501","http:\/\/api.twitter.com\/1\/users\/show.json?user_id=74447856","http:\/\/api.twitter.com\/1\/users\/show.json?user_id=21125645","http:\/\/api.twitter.com\/1\/users\/show.json?user_id=53666972","http:\/\/api.twitter.com\/1\/users\/show.json?user_id=115094500","http:\/\/api.twitter.com\/1\/users\/show.json?user_id=47666037","http:\/\/api.twitter.com\/1\/users\/show.json?user_id=67278209","http:\/\/api.twitter.com\/1\/users\/show.json?user_id=5138291","http:\/\/api.twitter.com\/1\/users\/show.json?user_id=81341924","http:\/\/api.twitter.com\/1\/users\/show.json?user_id=125603060","http:\/\/api.twitter.com\/1\/users\/show.json?user_id=43342755","http:\/\/api.twitter.com\/1\/users\/show.json?user_id=130620134","http:\/\/api.twitter.com\/1\/users\/show.json?user_id=86049905","http:\/\/api.twitter.com\/1\/users\/show.json?user_id=206623954","http:\/\/api.twitter.com\/1\/users\/show.json?user_id=98130292","http:\/\/api.twitter.com\/1\/users\/show.json?user_id=22471677","http:\/\/api.twitter.com\/1\/users\/show.json?user_id=44578624","http:\/\/api.twitter.com\/1\/users\/show.json?user_id=168482405","http:\/\/api.twitter.com\/1\/users\/show.json?user_id=21125553","http:\/\/api.twitter.com\/1\/users\/show.json?user_id=63448298","http:\/\/api.twitter.com\/1\/users\/show.json?user_id=80081085","http:\/\/api.twitter.com\/1\/users\/show.json?user_id=17308639","http:\/\/api.twitter.com\/1\/users\/show.json?user_id=179106488","http:\/\/api.twitter.com\/1\/users\/show.json?user_id=6716782","http:\/\/api.twitter.com\/1\/users\/show.json?user_id=83517833","http:\/\/api.twitter.com\/1\/users\/show.json?user_id=19470289","http:\/\/api.twitter.com\/1\/users\/show.json?user_id=14660652","http:\/\/api.twitter.com\/1\/users\/show.json?user_id=15632127","http:\/\/api.twitter.com\/1\/users\/show.json?user_id=22117978","http:\/\/api.twitter.com\/1\/users\/show.json?user_id=16996449","http:\/\/api.twitter.com\/1\/users\/show.json?user_id=77281450","http:\/\/api.twitter.com\/1\/users\/show.json?user_id=15691219","http:\/\/api.twitter.com\/1\/users\/show.json?user_id=77841866","http:\/\/api.twitter.com\/1\/users\/show.json?user_id=19227095","http:\/\/api.twitter.com\/1\/users\/show.json?user_id=70698817","http:\/\/api.twitter.com\/1\/users\/show.json?user_id=106164686","http:\/\/api.twitter.com\/1\/users\/show.json?user_id=51086080","http:\/\/api.twitter.com\/1\/users\/show.json?user_id=154571528","http:\/\/api.twitter.com\/1\/users\/show.json?user_id=13018982","http:\/\/api.twitter.com\/1\/users\/show.json?user_id=43017642","http:\/\/api.twitter.com\/1\/users\/show.json?user_id=16580210","http:\/\/api.twitter.com\/1\/users\/show.json?user_id=15405165","http:\/\/api.twitter.com\/1\/users\/show.json?user_id=1558651","http:\/\/api.twitter.com\/1\/users\/show.json?user_id=15161398","http:\/\/api.twitter.com\/1\/users\/show.json?user_id=15451529","http:\/\/api.twitter.com\/1\/users\/show.json?user_id=56958692","http:\/\/api.twitter.com\/1\/users\/show.json?user_id=6776952","http:\/\/api.twitter.com\/1\/users\/show.json?user_id=19182991","http:\/\/api.twitter.com\/1\/users\/show.json?user_id=88656441","http:\/\/api.twitter.com\/1\/users\/show.json?user_id=22057580","http:\/\/api.twitter.com\/1\/users\/show.json?user_id=15271509","http:\/\/api.twitter.com\/1\/users\/show.json?user_id=42713062","http:\/\/api.twitter.com\/1\/users\/show.json?user_id=16576302","http:\/\/api.twitter.com\/1\/users\/show.json?user_id=17207710","http:\/\/api.twitter.com\/1\/users\/show.json?user_id=8018382","http:\/\/api.twitter.com\/1\/users\/show.json?user_id=148681663","http:\/\/api.twitter.com\/1\/users\/show.json?user_id=143621049","http:\/\/api.twitter.com\/1\/users\/show.json?user_id=24381940","http:\/\/api.twitter.com\/1\/users\/show.json?user_id=131586391","http:\/\/api.twitter.com\/1\/users\/show.json?user_id=70329810","http:\/\/api.twitter.com\/1\/users\/show.json?user_id=14210469","http:\/\/api.twitter.com\/1\/users\/show.json?user_id=19645096","http:\/\/api.twitter.com\/1\/users\/show.json?user_id=130753065","http:\/\/api.twitter.com\/1\/users\/show.json?user_id=14688446","http:\/\/api.twitter.com\/1\/users\/show.json?user_id=136879221","http:\/\/api.twitter.com\/1\/users\/show.json?user_id=86032178","http:\/\/api.twitter.com\/1\/users\/show.json?user_id=45848011","http:\/\/api.twitter.com\/1\/users\/show.json?user_id=26962623","http:\/\/api.twitter.com\/1\/users\/show.json?user_id=1495591","http:\/\/api.twitter.com\/1\/users\/show.json?user_id=2048881","http:\/\/api.twitter.com\/1\/users\/show.json?user_id=139313482","http:\/\/api.twitter.com\/1\/users\/show.json?user_id=139129048","http:\/\/api.twitter.com\/1\/users\/show.json?user_id=65110417","http:\/\/api.twitter.com\/1\/users\/show.json?user_id=10832012","http:\/\/api.twitter.com\/1\/users\/show.json?user_id=75091295","http:\/\/api.twitter.com\/1\/users\/show.json?user_id=6671642","http:\/\/api.twitter.com\/1\/users\/show.json?user_id=15134307","http:\/\/api.twitter.com\/1\/users\/show.json?user_id=123927830","http:\/\/api.twitter.com\/1\/users\/show.json?user_id=49314234","http:\/\/api.twitter.com\/1\/users\/show.json?user_id=27460101","http:\/\/api.twitter.com\/1\/users\/show.json?user_id=14558214","http:\/\/api.twitter.com\/1\/users\/show.json?user_id=18555447","http:\/\/api.twitter.com\/1\/users\/show.json?user_id=9503802","http:\/\/api.twitter.com\/1\/users\/show.json?user_id=117099995","http:\/\/api.twitter.com\/1\/users\/show.json?user_id=70997383","http:\/\/api.twitter.com\/1\/users\/show.json?user_id=77755047","http:\/\/api.twitter.com\/1\/users\/show.json?user_id=112808918","http:\/\/api.twitter.com\/1\/users\/show.json?user_id=17893238","http:\/\/api.twitter.com\/1\/users\/show.json?user_id=16589206","http:\/\/api.twitter.com\/1\/users\/show.json?user_id=14198044","http:\/\/api.twitter.com\/1\/users\/show.json?user_id=15882926","http:\/\/api.twitter.com\/1\/users\/show.json?user_id=23439446","http:\/\/api.twitter.com\/1\/users\/show.json?user_id=24172026","http:\/\/api.twitter.com\/1\/users\/show.json?user_id=54493154","http:\/\/api.twitter.com\/1\/users\/show.json?user_id=30059867","http:\/\/api.twitter.com\/1\/users\/show.json?user_id=58761933","http:\/\/api.twitter.com\/1\/users\/show.json?user_id=14859899","http:\/\/api.twitter.com\/1\/users\/show.json?user_id=17448796","http:\/\/api.twitter.com\/1\/users\/show.json?user_id=3192451","http:\/\/api.twitter.com\/1\/users\/show.json?user_id=78100114","http:\/\/api.twitter.com\/1\/users\/show.json?user_id=29950811","http:\/\/api.twitter.com\/1\/users\/show.json?user_id=24611496","http:\/\/api.twitter.com\/1\/users\/show.json?user_id=86908939","http:\/\/api.twitter.com\/1\/users\/show.json?user_id=52162352","http:\/\/api.twitter.com\/1\/users\/show.json?user_id=35770778","http:\/\/api.twitter.com\/1\/users\/show.json?user_id=20841827","http:\/\/api.twitter.com\/1\/users\/show.json?user_id=20777380","http:\/\/api.twitter.com\/1\/users\/show.json?user_id=16345103","http:\/\/api.twitter.com\/1\/users\/show.json?user_id=5707672","http:\/\/api.twitter.com\/1\/users\/show.json?user_id=26725244","http:\/\/api.twitter.com\/1\/users\/show.json?user_id=12517882","http:\/\/api.twitter.com\/1\/users\/show.json?user_id=14292774","http:\/\/api.twitter.com\/1\/users\/show.json?user_id=85630240","http:\/\/api.twitter.com\/1\/users\/show.json?user_id=27516037","http:\/\/api.twitter.com\/1\/users\/show.json?user_id=17185997","http:\/\/api.twitter.com\/1\/users\/show.json?user_id=63529843","http:\/\/api.twitter.com\/1\/users\/show.json?user_id=42969356","http:\/\/api.twitter.com\/1\/users\/show.json?user_id=77733443","http:\/\/api.twitter.com\/1\/users\/show.json?user_id=19072599","http:\/\/api.twitter.com\/1\/users\/show.json?user_id=15456974","http:\/\/api.twitter.com\/1\/users\/show.json?user_id=50423172","http:\/\/api.twitter.com\/1\/users\/show.json?user_id=23085153","http:\/\/api.twitter.com\/1\/users\/show.json?user_id=37898529","http:\/\/api.twitter.com\/1\/users\/show.json?user_id=17000971","http:\/\/api.twitter.com\/1\/users\/show.json?user_id=82204193","http:\/\/api.twitter.com\/1\/users\/show.json?user_id=64358875","http:\/\/api.twitter.com\/1\/users\/show.json?user_id=48628192","http:\/\/api.twitter.com\/1\/users\/show.json?user_id=60548383","http:\/\/api.twitter.com\/1\/users\/show.json?user_id=50478051","http:\/\/api.twitter.com\/1\/users\/show.json?user_id=84354670","http:\/\/api.twitter.com\/1\/users\/show.json?user_id=83122319","http:\/\/api.twitter.com\/1\/users\/show.json?user_id=84554936","http:\/\/api.twitter.com\/1\/users\/show.json?user_id=17107158","http:\/\/api.twitter.com\/1\/users\/show.json?user_id=16468998","http:\/\/api.twitter.com\/1\/users\/show.json?user_id=15904103","http:\/\/api.twitter.com\/1\/users\/show.json?user_id=24545235","http:\/\/api.twitter.com\/1\/users\/show.json?user_id=84316042","http:\/\/api.twitter.com\/1\/users\/show.json?user_id=49395645","http:\/\/api.twitter.com\/1\/users\/show.json?user_id=73628167","http:\/\/api.twitter.com\/1\/users\/show.json?user_id=71335987","http:\/\/api.twitter.com\/1\/users\/show.json?user_id=31417063","http:\/\/api.twitter.com\/1\/users\/show.json?user_id=5321152","http:\/\/api.twitter.com\/1\/users\/show.json?user_id=25052706","http:\/\/api.twitter.com\/1\/users\/show.json?user_id=14871080","http:\/\/api.twitter.com\/1\/users\/show.json?user_id=43325643","http:\/\/api.twitter.com\/1\/users\/show.json?user_id=44342717","http:\/\/api.twitter.com\/1\/users\/show.json?user_id=14461032","http:\/\/api.twitter.com\/1\/users\/show.json?user_id=9720292","http:\/\/api.twitter.com\/1\/users\/show.json?user_id=16258124","http:\/\/api.twitter.com\/1\/users\/show.json?user_id=14823109","http:\/\/api.twitter.com\/1\/users\/show.json?user_id=46210632","http:\/\/api.twitter.com\/1\/users\/show.json?user_id=5548772","http:\/\/api.twitter.com\/1\/users\/show.json?user_id=24881096","http:\/\/api.twitter.com\/1\/users\/show.json?user_id=19863714","http:\/\/api.twitter.com\/1\/users\/show.json?user_id=35493627"],"mentions":{"junicks":30,"CarFreiTag":26,"excalibaxe":16,"fatmike182":16,"marcoschreuder":12,"TomEnzi":10,"wslchen":9,"hofrat":8,"kewagi":8,"Kratochvil":6,"klapauz":5,"countsickness":5,"dieNagashi":5,"PrinceznaAndrea":5,"pseudobit":5,"bobschi":4,"TymonTyco":4,"Philoponus":4,"thesandworm":4,"andiheimann":3,"MartinSchimak":3,"Iossif":3,"EdWohlfahrt":3,"mariamonaco":3,"edu":3,"zwetschken":3,"DiePressecom":3,"severinmayr":3,"TheSandworm":3,"hmjahnel":2,"zebramaedchen":2,"gotsen":2,"georgholzer":2,"Karli":2,"SemiSemotan":2,"Helge":2,"issi":2,"Trias_":2,"janasichtbar":2,"WernerReisinger":2,"GreenpeaceAT":2,"Dyrnberg":2,"JonasReisWien":2,"_Capitalism_":2,"peterglaser":2,"leningratt":2,"gewure":2,"jackoty":2,"der_ak":2,"MasterRed2":1,"Don_Haeberle":1,"leyrer":1,"MesiMarie":1,"againcoa":1,"pinkostar":1,"NancyODell":1,"helge":1,"oe1":1,"derstandard":1,"Poscoleri":1,"Nattl":1,"hirnduebel":1,"polymo":1,"Anni_Versum":1,"danimrich":1,"windprincess":1,"mentioned":1,"chorherr":1,"mihi_tr":1,"annelinja":1,"bioseraser":1,"wolfgang_thies":1,"tymontyco":1,"SuperMarki":1,"format_at":1,"BrandiATMuhkuh":1,"zonkinoff":1,"Weltregierung":1,"Dragnous":1,"poscoleri":1,"mebner":1,"obama":1,"bush":1,"schuessel":1,"oe3":1,"thebalancebeam":1,"binladen":1,"mubarak":1,"RolandGiersig":1,"strasser":1,"grasser":1,"gaddafi":1,"misik":1},"scientific_events":[],"persons":[],"places":[],"general_events":[],"organisations":[],"tags":{"unibrennt":7,"twitter":4,"ff":4,"neusprech":4,"facebook":4,"lol":3,"bettelverbot":3,"tugraz":3,"guttenberg":2,"followerpow":2,"kfu":2,"yen":2,"club2":2,"jfyi":1,"uni":1,"a1":1,"barprojekt":1,"nonsensetweet":1,"appl":1,"fifa11":1,"opernbal":1,"seitenhieb":1,"musiclobbi":1,"tutdasnot":1,"kottulinski":1,"supermarktkettenverbot":1,"texta":1,"twittermanieren":1,"kaffeeverbot":1,"judenstern":1,"emotweet":1,"twittervot":1,"voratsdatenspeicherung":1,"rotweissrotcard":1,"fb":1,"atomkraft":1,"tweetdeck":1,"VDS":1,"foursquar":1,"diaspora":1,"sexismu":1,"Wahnsinnsbild":1,"planbett":1,"projektmanag":1,"Graz":1,"Vorratsdatenspeicherung":1,"vd":1,"wikileak":1,"thedoor":1,"fremdschaem":1,"urgestein":1,"hitlerbart":1,"Piraten":1,"FollowFridai":1,"justizausschuss":1,"ichwerdpolitik":1,"nowplai":1,"powerfick":1,"twitterwal":1,"gadi2011":1,"jobtweet":1}}